markdowntopdf/__init__.py
markdowntopdf/css/default.css
markdowntopdf/markdowntopdf.py
markdowntopdf/pygments-css/README.md
markdowntopdf/pygments-css/UNLICENSE.txt
markdowntopdf/pygments-css/autumn.css
markdowntopdf/pygments-css/borland.css
markdowntopdf/pygments-css/bw.css
markdowntopdf/pygments-css/colorful.css
markdowntopdf/pygments-css/default.css
markdowntopdf/pygments-css/emacs.css
markdowntopdf/pygments-css/friendly.css
markdowntopdf/pygments-css/fruity.css
markdowntopdf/pygments-css/makefile
markdowntopdf/pygments-css/manni.css
markdowntopdf/pygments-css/monokai.css
markdowntopdf/pygments-css/murphy.css
markdowntopdf/pygments-css/native.css
markdowntopdf/pygments-css/package.json
markdowntopdf/pygments-css/pastie.css
markdowntopdf/pygments-css/perldoc.css
markdowntopdf/pygments-css/requirements.txt
markdowntopdf/pygments-css/tango.css
markdowntopdf/pygments-css/trac.css
markdowntopdf/pygments-css/vim.css
markdowntopdf/pygments-css/vs.css
markdowntopdf-0.1.3.dist-info/LICENSE
markdowntopdf-0.1.3.dist-info/METADATA
markdowntopdf-0.1.3.dist-info/WHEEL
markdowntopdf-0.1.3.dist-info/entry_points.txt
markdowntopdf-0.1.3.dist-info/RECORD
